nonebot_plugin_copywrite/__init__.py
nonebot_plugin_copywrite/chat.py
nonebot_plugin_copywrite/config.py
nonebot_plugin_copywrite/copywrite/__init__.py
nonebot_plugin_copywrite/copywrite/default.long.yaml
nonebot_plugin_copywrite/copywrite/default.short.yaml
nonebot_plugin_copywrite/copywrite/fran.long.yaml
nonebot_plugin_copywrite/copywrite/fran.short.yaml
nonebot_plugin_copywrite/copywrite/life.checkpoint.long.yaml
nonebot_plugin_copywrite/copywrite/sujoke.short.yaml
nonebot_plugin_copywrite-0.3.0.dist-info/METADATA
nonebot_plugin_copywrite-0.3.0.dist-info/WHEEL
nonebot_plugin_copywrite-0.3.0.dist-info/licenses/LICENSE
nonebot_plugin_copywrite-0.3.0.dist-info/RECORD
