Metadata-Version: 2.4
Name: nonebot-plugin-copywrite
Version: 0.3.0
Author-email: Yan <1964649083@qq.com>
License-Expression: Apache-2.0
License-File: LICENSE
Requires-Python: <4.0,>=3.11
Requires-Dist: cairosvg<3,>=2.7.1
Requires-Dist: nonebot-adapter-onebot<3,>=2.4.6
Requires-Dist: nonebot2<3,>=2.4.0
Requires-Dist: openai<2,>=1.54.3
Requires-Dist: pyyaml<7,>=6.0.1
